toughbt/__init__.py
toughbt/auth_master.py
toughbt/auth_worker.py
toughbt/choosereactor.py
toughbt/dictionary
toughbt/mputils.py
toughbt/radius_benchmark.py
toughbt/radiusclient.py
toughbt-0.0.7.data/scripts/trbctl
toughbt-0.0.7.dist-info/DESCRIPTION.rst
toughbt-0.0.7.dist-info/METADATA
toughbt-0.0.7.dist-info/RECORD
toughbt-0.0.7.dist-info/WHEEL
toughbt-0.0.7.dist-info/eager_resources.txt
toughbt-0.0.7.dist-info/metadata.json
toughbt-0.0.7.dist-info/top_level.txt
toughbt-0.0.7.dist-info/zip-safe
