Metadata-Version: 2.0
Name: toughbt
Version: 0.0.7
Summary: RADIUS tools
Home-page: https://github.com/toughmen/toughradius-benchmark
Author: toughmen
Author-email: wjt.net@outlook.com
License: GPL
Keywords: radius,AAA,authentication,accounting,authorization,toughradius,benchmark
Platform: UNKNOWN
Classifier: Development Status :: 6 - Mature
Classifier: Intended Audience :: Developers
Classifier: Programming Language :: Python :: 2.6
Classifier: Programming Language :: Python :: 2.7
Classifier: Topic :: Software Development :: Libraries :: Python Modules
Classifier: Topic :: System :: Systems Administration :: Authentication/Directory
Requires-Dist: Twisted (>=15.0.0)
Requires-Dist: six (>=1.8.0)
Requires-Dist: txradius
Requires-Dist: txzmq
